test/__init__.py
webmoney-0.0.1.dist-info/METADATA
webmoney-0.0.1.dist-info/WHEEL
webmoney-0.0.1.dist-info/top_level.txt
webmoney-0.0.1.dist-info/RECORD
