Metadata-Version: 2.1
Name: webmoney
Version: 0.0.1
Summary: don't use it
Home-page: https://github.com/xxxcrystalcastles
Author: xxxcrystalcastles
Author-email: fastcat1991@gmail.com
License: MIT
Platform: UNKNOWN
Classifier: License :: OSI Approved :: MIT License
Classifier: Programming Language :: Python :: 3
Classifier: Programming Language :: Python :: 3.6
